[{"args":{"child":"195.12.188.34","parent":"195.8.218.131"},"level":"NOTICE","module":"DNSSEC","tag":"NEITHER_DNSKEY_NOR_DS","testcase":"DNSSEC07","timestamp":0.0442497730255127},{"args":{"zone":"draugelis.lt"},"level":"NOTICE","module":"DNSSEC","tag":"NOT_SIGNED","testcase":"UNSPECIFIED","timestamp":0.0448338985443115},{"args":{"ns":"ns2.domreg.lt/2001:778:0:8::8"},"level":"WARNING","module":"NAMESERVER","tag":"NS_ERROR","testcase":"NAMESERVER02","timestamp":0.0860509872436523},{"args":{"ns":"ns2.domreg.lt/83.171.8.8"},"level":"WARNING","module":"NAMESERVER","tag":"NS_ERROR","testcase":"NAMESERVER02","timestamp":0.0889499187469482},{"args":{"ns":"ns2.domreg.lt/2001:778:0:8::8","rcode":"REFUSED"},"level":"WARNING","module":"NAMESERVER","tag":"A_UNEXPECTED_RCODE","testcase":"NAMESERVER05","timestamp":0.115612983703613},{"args":{"ns":"ns2.domreg.lt/83.171.8.8","rcode":"REFUSED"},"level":"WARNING","module":"NAMESERVER","tag":"A_UNEXPECTED_RCODE","testcase":"NAMESERVER05","timestamp":0.118623971939087},{"args":{"ns":"ns2.domreg.lt/2001:778:0:8::8"},"level":"WARNING","module":"NAMESERVER","tag":"NS_ERROR","testcase":"NAMESERVER12","timestamp":0.177659034729004},{"args":{"ns":"ns2.domreg.lt/83.171.8.8"},"level":"WARNING","module":"NAMESERVER","tag":"NS_ERROR","testcase":"NAMESERVER12","timestamp":0.180429935455322},{"args":{"ns":"ns2.domreg.lt/2001:778:0:8::8"},"level":"WARNING","module":"NAMESERVER","tag":"NS_ERROR","testcase":"NAMESERVER13","timestamp":0.182374000549316},{"args":{"ns":"ns2.domreg.lt/83.171.8.8"},"level":"WARNING","module":"NAMESERVER","tag":"NS_ERROR","testcase":"NAMESERVER13","timestamp":0.182545900344849}]
